repo_sanitize/__init__.py
repo_sanitize/__main__.py
repo_sanitize/cli.py
repo_sanitize/config.py
repo_sanitize/core.py
repo_sanitize/git_tools.py
repo_sanitize-0.1.0.dist-info/LICENSE
repo_sanitize-0.1.0.dist-info/METADATA
repo_sanitize-0.1.0.dist-info/WHEEL
repo_sanitize-0.1.0.dist-info/entry_points.txt
repo_sanitize-0.1.0.dist-info/RECORD
