Metadata-Version: 2.3
Name: repo-sanitize
Version: 0.1.0
Summary: Basic package to clean up github repos, removing secrets or env variables that arent supposed to be there.
License: MIT
Author: 0rac130fD31phi
Author-email: william.astley@algebraicwealth.com
Requires-Python: >=3.12
Classifier: License :: OSI Approved :: MIT License
Classifier: Programming Language :: Python :: 3
Classifier: Programming Language :: Python :: 3.12
Classifier: Programming Language :: Python :: 3.13
Requires-Dist: dotenv (>=0.9.9,<0.10.0)
Requires-Dist: rich (>=14.0.0,<15.0.0)
